common_py/__init__.py
common_py/dict_extension.py
common_py/enum_argparse.py
common_py/file.py
common_py/folder.py
common_py/list_extension.py
common_py/sftp.py
common_py/dl/__init__.py
common_py/dl/report.py
common_py/dl/report_slack.py
common_py/functional/__init__.py
common_py/functional/either.py
common_py/functional/future.py
common_py/functional/monad.py
common_py/functional/option.py
common_py-0.1.4.dist-info/LICENSE
common_py-0.1.4.dist-info/METADATA
common_py-0.1.4.dist-info/WHEEL
common_py-0.1.4.dist-info/top_level.txt
common_py-0.1.4.dist-info/RECORD
