Metadata-Version: 2.1
Name: common-py
Version: 0.1.4
Summary: The fundamental package needed for common purpose with Python.
Home-page: https://github.com/tenkeyless/common_py
Author: TenKeyLess
Author-email: blivme84@naver.com
License: MIT
Keywords: common util
Platform: UNKNOWN
Classifier: Intended Audience :: Developers
Classifier: Programming Language :: Python :: 3.7
Classifier: License :: OSI Approved :: MIT License
Classifier: Operating System :: MacOS
Classifier: Operating System :: Unix
Requires-Python: >=3.7
Requires-Dist: toolz (>=0.10.0)
Requires-Dist: matplotlib (>=3.1.1)
Requires-Dist: paramiko (>=2.7.1)
